mtasr/__init__.py
mtasr/asr_pb2.py
mtasr/asr_pb2_grpc.py
mtasr/grpc_client.py
mtasr-1.1.2.dist-info/LICENSE
mtasr-1.1.2.dist-info/METADATA
mtasr-1.1.2.dist-info/WHEEL
mtasr-1.1.2.dist-info/top_level.txt
mtasr-1.1.2.dist-info/RECORD
